pytoplot/__init__.py
pytoplot/pyToplot_mod.py
pytoplot/pytoplot.py
pytoplot-1.0.3.dist-info/METADATA
pytoplot-1.0.3.dist-info/WHEEL
pytoplot-1.0.3.dist-info/top_level.txt
pytoplot-1.0.3.dist-info/RECORD
