Metadata-Version: 2.1
Name: pytoplot
Version: 1.0.3
Summary: Visualization tool for the PL2D option of the TOPOND module of the CRYSTAL software
Home-page: UNKNOWN
Author: Alessandro Cossard
Author-email: <alessandro.cossard@unito.it>
License: UNKNOWN
Keywords: python,chemistry,physics,crystal,topond,quantum
Platform: UNKNOWN
Classifier: Development Status :: 1 - Planning
Classifier: Intended Audience :: Developers
Classifier: Programming Language :: Python :: 3
Classifier: Operating System :: Unix
Classifier: Operating System :: MacOS :: MacOS X
Classifier: Operating System :: Microsoft :: Windows
